Metadata-Version: 2.1
Name: ee059f4560b24ba78d7c30103ea49713
Version: 0.0.1
Summary: ee059f4560b24ba78d7c30103ea49713
Home-page: https://pypi.python.org/pypi/ee059f4560b24ba78d7c30103ea49713/
Author: Username
License: gpl-3.0
Platform: UNKNOWN
Classifier: Development Status :: 3 - Alpha
Classifier: License :: OSI Approved :: GNU General Public License v3 (GPLv3)
Classifier: Programming Language :: Python :: 3.6
License-File: LICENSE.txt
